http_log_parser/__init__.py
http_log_parser/__main__.py
http_log_parser/_entry_point.py
http_log_parser/nginx_parser.py
http_log_parser-0.2.0.dist-info/entry_points.txt
http_log_parser-0.2.0.dist-info/WHEEL
http_log_parser-0.2.0.dist-info/METADATA
http_log_parser-0.2.0.dist-info/RECORD
