Metadata-Version: 2.1
Name: http-log-parser
Version: 0.2.0
Summary: Cli tool to parse stream of http access events into json formatted events.
Requires-Python: >=3.6,<4.0
Classifier: Programming Language :: Python :: 3
Classifier: Programming Language :: Python :: 3.6
Classifier: Programming Language :: Python :: 3.7
Classifier: Programming Language :: Python :: 3.8
Classifier: Programming Language :: Python :: 3.9
